{
  "projectId": "fintech-requisitions",
  "appId": "1:2730554389:web:eaf336c107434ef442ca1c",
  "apiKey": "AIzaSyCTAlP2_HARk1MYqUv1W_HxfIaRQCtC-HY",
  "authDomain": "fintech-requisitions.firebaseapp.com",
  "firestoreDatabaseId": "ai-studio-standrewsrequisi-4557280f-c588-4a23-9ac4-307fc42213b4",
  "storageBucket": "fintech-requisitions.firebasestorage.app",
  "messagingSenderId": "2730554389",
  "measurementId": "",
  "oAuthClientId": "2730554389-3q43u12rffgkd2bfjbamvsga8estn1pi.apps.googleusercontent.com"
}